fleetfluid/__init__.py
fleetfluid/core.py
fleetfluid/models.py
fleetfluid/modes/__init__.py
fleetfluid/modes/base.py
fleetfluid/modes/cloud.py
fleetfluid/modes/factory.py
fleetfluid/modes/opensource.py
fleetfluid-0.1.6.dist-info/licenses/LICENSE
fleetfluid-0.1.6.dist-info/METADATA
fleetfluid-0.1.6.dist-info/WHEEL
fleetfluid-0.1.6.dist-info/top_level.txt
fleetfluid-0.1.6.dist-info/RECORD
