Metadata-Version: 2.4
Name: fleetfluid
Version: 0.1.6
Summary: AI Agent Functions for ETL/Data Processing
Author-email: Andreyo <bobroe.web@gmail.com>
License: MIT
Project-URL: Homepage, https://github.com/vossmoos/fleetfluid
Project-URL: Repository, https://github.com/vossmoos/fleetfluid
Project-URL: Issues, https://github.com/vossmoos/fleetfluid/issues
Keywords: ai,etl,data-processing,text-processing,pydantic-ai,llm
Classifier: Development Status :: 3 - Alpha
Classifier: Intended Audience :: Developers
Classifier: License :: OSI Approved :: MIT License
Classifier: Operating System :: OS Independent
Classifier: Programming Language :: Python :: 3
Classifier: Programming Language :: Python :: 3.8
Classifier: Programming Language :: Python :: 3.9
Classifier: Programming Language :: Python :: 3.10
Classifier: Programming Language :: Python :: 3.11
Classifier: Programming Language :: Python :: 3.12
Classifier: Topic :: Software Development :: Libraries :: Python Modules
Classifier: Topic :: Scientific/Engineering :: Artificial Intelligence
Classifier: Topic :: Text Processing
Requires-Python: >=3.8
License-File: LICENSE
Requires-Dist: pydantic-ai
Requires-Dist: pydantic
Requires-Dist: httpx
Provides-Extra: dev
Requires-Dist: pytest>=6.0; extra == "dev"
Requires-Dist: pytest-asyncio; extra == "dev"
Requires-Dist: black; extra == "dev"
Requires-Dist: isort; extra == "dev"
Requires-Dist: mypy; extra == "dev"
Dynamic: license-file
